picdate/__init__.py
picdate/picdate.py
picdate-2.1.0.dist-info/LICENSE
picdate-2.1.0.dist-info/METADATA
picdate-2.1.0.dist-info/WHEEL
picdate-2.1.0.dist-info/entry_points.txt
picdate-2.1.0.dist-info/top_level.txt
picdate-2.1.0.dist-info/RECORD
