Metadata-Version: 2.2
Name: picdate
Version: 2.1.0
Summary: PicDate: Quick and Simple Date Marking for Photos
Author-email: Po-Hsuan Huang <aben20807@gmail.com>
License: The MIT License (MIT)
Project-URL: Homepage, https://github.com/aben20807/picdate
Project-URL: Bug Tracker, https://github.com/aben20807/picdate/issues
Classifier: Programming Language :: Python :: 3 :: Only
Classifier: License :: OSI Approved :: MIT License
Classifier: Operating System :: OS Independent
Classifier: Topic :: Multimedia :: Graphics
Requires-Python: >=3.8
License-File: LICENSE
Requires-Dist: pillow
